ptvsd/ThirdPartyNotices.txt
ptvsd/__init__.py
ptvsd/__main__.py
ptvsd/_local.py
ptvsd/_remote.py
ptvsd/_util.py
ptvsd/_version.py
ptvsd/attach_script_ptvsd_pid.py
ptvsd/attach_server.py
ptvsd/compat.py
ptvsd/daemon.py
ptvsd/debugger.py
ptvsd/exit_handlers.py
ptvsd/futures.py
ptvsd/ipcjson.py
ptvsd/log.py
ptvsd/messaging.py
ptvsd/multiproc.py
ptvsd/options.py
ptvsd/pydevd_hooks.py
ptvsd/reraise.py
ptvsd/reraise2.py
ptvsd/reraise3.py
ptvsd/runner.py
ptvsd/session.py
ptvsd/socket.py
ptvsd/tracing.py
ptvsd/version.py
ptvsd/wrapper.py
ptvsd/_vendored/__init__.py
ptvsd/_vendored/_pydevd_packaging.py
ptvsd/_vendored/_util.py
ptvsd/_vendored/force_pydevd.py
ptvsd/_vendored/pydevd/pydev_app_engine_debug_startup.py
ptvsd/_vendored/pydevd/pydev_coverage.py
ptvsd/_vendored/pydevd/pydev_pysrc.py
ptvsd/_vendored/pydevd/pydev_run_in_console.py
ptvsd/_vendored/pydevd/pydevconsole.py
ptvsd/_vendored/pydevd/pydevd.py
ptvsd/_vendored/pydevd/pydevd_file_utils.py
ptvsd/_vendored/pydevd/pydevd_tracing.py
ptvsd/_vendored/pydevd/setup_cython.py
ptvsd/_vendored/pydevd/_pydev_bundle/__init__.py
ptvsd/_vendored/pydevd/_pydev_bundle/_pydev_calltip_util.py
ptvsd/_vendored/pydevd/_pydev_bundle/_pydev_completer.py
ptvsd/_vendored/pydevd/_pydev_bundle/_pydev_filesystem_encoding.py
ptvsd/_vendored/pydevd/_pydev_bundle/_pydev_getopt.py
ptvsd/_vendored/pydevd/_pydev_bundle/_pydev_imports_tipper.py
ptvsd/_vendored/pydevd/_pydev_bundle/_pydev_jy_imports_tipper.py
ptvsd/_vendored/pydevd/_pydev_bundle/_pydev_log.py
ptvsd/_vendored/pydevd/_pydev_bundle/_pydev_tipper_common.py
ptvsd/_vendored/pydevd/_pydev_bundle/pydev_console_utils.py
ptvsd/_vendored/pydevd/_pydev_bundle/pydev_import_hook.py
ptvsd/_vendored/pydevd/_pydev_bundle/pydev_imports.py
ptvsd/_vendored/pydevd/_pydev_bundle/pydev_ipython_console.py
ptvsd/_vendored/pydevd/_pydev_bundle/pydev_ipython_console_011.py
ptvsd/_vendored/pydevd/_pydev_bundle/pydev_is_thread_alive.py
ptvsd/_vendored/pydevd/_pydev_bundle/pydev_localhost.py
ptvsd-4.3.2.dist-info/LICENSE
ptvsd-4.3.2.dist-info/METADATA
ptvsd-4.3.2.dist-info/WHEEL
ptvsd-4.3.2.dist-info/top_level.txt
ptvsd-4.3.2.dist-info/RECORD
