Metadata-Version: 2.1
Name: ptvsd
Version: 4.3.2
Summary: Remote debugging server for Python support in Visual Studio and Visual Studio Code
Home-page: https://aka.ms/ptvs
Author: Microsoft Corporation
Author-email: ptvshelp@microsoft.com
License: MIT
Platform: win32
Classifier: Development Status :: 5 - Production/Stable
Classifier: Programming Language :: Python :: 2.7
Classifier: Programming Language :: Python :: 3.4
Classifier: Programming Language :: Python :: 3.5
Classifier: Programming Language :: Python :: 3.6
Classifier: Programming Language :: Python :: 3.7
Classifier: Topic :: Software Development :: Debuggers
Classifier: Operating System :: OS Independent
Classifier: License :: OSI Approved :: Eclipse Public License 2.0 (EPL-2.0)
Classifier: License :: OSI Approved :: MIT License
Requires-Python: >=2.7,!=3.0.*,!=3.1.*,!=3.2.*,!=3.3.*
